[
    {
        "uuid": "12345",
        "po_number": "12345",
        "tier_1": "Thyssen Krupp",
        "product_description": "Lenkgetriebe",
        "mpn": "TLE5309D E1211",
        "manufacturer": "Infineon",
        "quantity": 150000.0,
        "price_per_unit_eur": 50.0,
        "order_volume_eur": 7500000.0,
        "price_per_unit_usd": 0.0,
        "order_volume_usd": 0.0,
        "broker": "",
        "eta_at_btv": "09.03.23",
        "eta_at_tier_1": "14.03.23",
        "tracking": [
            {
                "order_date": "2023-03-01",
                "parts_secured": "2023-03-02",
                "parts_secured_quantity": 120000.0,
                "arrival_date_at_testhouse": "2023-03-03",
                "successful_test": 10000.0,
                "failed_test": 140000.0,
                "parts_arrived_in_eu": "2023-03-06",
                "parts_arrived_in_eu_quantity": 50000.0,
                "actual_arrival_at_btv": "2023-03-08",
                "transportation_company_to_btv": "DHL",
                "tracking_link_to_btv": "https://www.google.com",
                "actual_delivered_quantity_to_btv": 30000.0,
                "actual_arrival_at_tier_1": "2023-03-10",
                "transportation_company_to_tier_1": "DHL",
                "tracking_link_to_tier_1": "https://www.google.com",
                "actual_delivered_quantity_to_tier_1": 100000.0
            },
            {
                "order_date": "2023-03-01",
                "parts_secured": "2023-03-02",
                "parts_secured_quantity": 150000.0,
                "arrival_date_at_testhouse": "2023-03-03",
                "successful_test": 50000.0,
                "failed_test": 100000.0,
                "parts_arrived_in_eu": "2023-03-06",
                "parts_arrived_in_eu_quantity": 50000.0,
                "actual_arrival_at_btv": "2023-03-08",
                "transportation_company_to_btv": "DHL",
                "tracking_link_to_btv": "https://www.google.com",
                "actual_delivered_quantity_to_btv": 30000.0,
                "actual_arrival_at_tier_1": "2023-03-10 ",
                "transportation_company_to_tier_1": "DHL",
                "tracking_link_to_tier_1": "https://www.google.com",
                "actual_delivered_quantity_to_tier_1": 100000.0
            }
        ],
        "comments": "1. Lorem Impsum.\n2. Dolor sit amet.\n3. Conseteur.\n4. Sadipscing elitr."
    },
    {
        "uuid": "56345",
        "po_number": "56345",
        "tier_1": "Borgwarner",
        "product_description": "Spannungseinbruchbegrenzer",
        "mpn": "TLE5309D E1211",
        "manufacturer": "Texas Instruments",
        "quantity": 150000.0,
        "price_per_unit_eur": 50.0,
        "order_volume_eur": 7500000.0,
        "price_per_unit_usd": 0.0,
        "order_volume_usd": 0.0,
        "broker": "",
        "eta_at_btv": "09.03.23",
        "eta_at_tier_1": "14.03.23",
        "tracking": [
            {
                "order_date": "2023-03-01",
                "parts_secured": "2023-03-08",
                "parts_secured_quantity": 150000.0,
                "arrival_date_at_testhouse": "2023-03-09",
                "successful_test": 50000.0,
                "failed_test": 100000.0,
                "parts_arrived_in_eu": "2023-03-10",
                "parts_arrived_in_eu_quantity": 50000.0,
                "actual_arrival_at_btv": "2023-03-14",
                "transportation_company_to_btv": "DHL",
                "tracking_link_to_btv": "https://www.google.com",
                "actual_delivered_quantity_to_btv": 30000.0,
                "actual_arrival_at_tier_1": "2023-03-18",
                "transportation_company_to_tier_1": "DHL",
                "tracking_link_to_tier_1": "https://www.google.com",
                "actual_delivered_quantity_to_tier_1": 100000.0
            }
        ],
        "comments": "1. Lorem Impsum.\n2. Dolor sit amet.\n3. Conseteur.\n4. Sadipscing elitr."
    }
]